gkdtex/__init__.py
gkdtex/builtins.py
gkdtex/cli.py
gkdtex/developer_utilities.py
gkdtex/interpreter.py
gkdtex/lex.py
gkdtex/parse.py
gkdtex/spelling.py
gkdtex/wrap.py
runtest/__init__.py
runtest/plugin_A.py
runtest/t2.py
gkdtex-0.4.1.dist-info/LICENSE
gkdtex-0.4.1.dist-info/METADATA
gkdtex-0.4.1.dist-info/WHEEL
gkdtex-0.4.1.dist-info/entry_points.txt
gkdtex-0.4.1.dist-info/top_level.txt
gkdtex-0.4.1.dist-info/RECORD
