Metadata-Version: 2.1
Name: gkdtex
Version: 0.4.1
Summary: A programmable TeX-compatible 2-stage typesetting language.
Home-page: https://github.com/thautwarm/gkdtex
Author: thautwarm
Author-email: twshere@outlook.com
License: mit
Keywords: LaTeX,TeX,typesetting,preprocessing,programming language
Platform: any
Classifier: Programming Language :: Python :: 3.6
Classifier: Programming Language :: Python :: 3.7
Classifier: Programming Language :: Python :: 3.8
Classifier: Programming Language :: Python :: Implementation :: CPython
Requires-Python: >=3.6.0
Requires-Dist: wisepy2 (>=1.0)
